django_esewa/Exceptions.py
django_esewa/__init__.py
django_esewa/payment.py
django_esewa/signature.py
django_esewa/utils.py
django_esewa-1.0.9.dist-info/licenses/LICENSE
esewa_tests/__init__.py
esewa_tests/test_signature.py
django_esewa-1.0.9.dist-info/METADATA
django_esewa-1.0.9.dist-info/WHEEL
django_esewa-1.0.9.dist-info/top_level.txt
django_esewa-1.0.9.dist-info/RECORD
